COPYING
README.md
pyproject.toml
setup.cfg
setup.py
whats_new.md
src/pubget/__init__.py
src/pubget/_articles.py
src/pubget/_authors.py
src/pubget/_commands.py
src/pubget/_coordinate_space.py
src/pubget/_coordinates.py
src/pubget/_data_extraction.py
src/pubget/_download.py
src/pubget/_entrez.py
src/pubget/_fit_neuroquery.py
src/pubget/_fit_neurosynth.py
src/pubget/_img_utils.py
src/pubget/_labelbuddy.py
src/pubget/_links.py
src/pubget/_metadata.py
src/pubget/_model_data.py
src/pubget/_nimare.py
src/pubget/_pipeline.py
src/pubget/_plugins.py
src/pubget/_text.py
src/pubget/_typing.py
src/pubget/_utils.py
src/pubget/_vectorization.py
src/pubget/_vocabulary.py
src/pubget/_writers.py
src/pubget.egg-info/PKG-INFO
src/pubget.egg-info/SOURCES.txt
src/pubget.egg-info/dependency_links.txt
src/pubget.egg-info/entry_points.txt
src/pubget.egg-info/not-zip-safe
src/pubget.egg-info/requires.txt
src/pubget.egg-info/top_level.txt
src/pubget/_data/VERSION
src/pubget/_data/_fit_neuroquery/README.md
src/pubget/_data/_fit_neuroquery/app.py
src/pubget/_data/_fit_neuroquery/requirements.txt
src/pubget/_data/_fit_neurosynth/README.md
src/pubget/_data/_fit_neurosynth/app.py
src/pubget/_data/_fit_neurosynth/requirements.txt
src/pubget/_data/stylesheets/table_extraction.xsl
src/pubget/_data/stylesheets/text_extraction.xsl
src/pubget/_data/stylesheets/docbook/AUTHORS
src/pubget/_data/stylesheets/docbook/BUGS
src/pubget/_data/stylesheets/docbook/COPYING
src/pubget/_data/stylesheets/docbook/INSTALL
src/pubget/_data/stylesheets/docbook/Makefile
src/pubget/_data/stylesheets/docbook/NEWS
src/pubget/_data/stylesheets/docbook/NEWS.html
src/pubget/_data/stylesheets/docbook/NEWS.xml
src/pubget/_data/stylesheets/docbook/README
src/pubget/_data/stylesheets/docbook/RELEASE-NOTES.html
src/pubget/_data/stylesheets/docbook/RELEASE-NOTES.txt
src/pubget/_data/stylesheets/docbook/RELEASE-NOTES.xml
src/pubget/_data/stylesheets/docbook/REVISION
src/pubget/_data/stylesheets/docbook/TODO
src/pubget/_data/stylesheets/docbook/VERSION
src/pubget/_data/stylesheets/docbook/VERSION.xsl
src/pubget/_data/stylesheets/docbook/build.xml
src/pubget/_data/stylesheets/docbook/catalog.xml
src/pubget/_data/stylesheets/docbook/install.sh
